tests/2b_locality_improved__length-0_id-1_od-1__test.py
tests/3a_subsequence__normalizer-none_maxlen-1_lambda-1__test.py
tests/1b_fixed_degree__degree-1__test.py
tests/2a_locality_improved__normalizer-none_length-0_id-1_od-1__test.py
tests/3b_subsequence__maxlen-1_lambda-1__test.py
tests/__init__.py
tests/1a_fixed_degree__normalizer-none_degree-1__test.py
strkernels-0.1.0.dist-info/LICENSE
strkernels-0.1.0.dist-info/WHEEL
strkernels-0.1.0.dist-info/top_level.txt
strkernels-0.1.0.dist-info/RECORD
strkernels-0.1.0.dist-info/METADATA
strkernels/string_kernel.py
strkernels/fixed_degree_string_kernel.py
strkernels/locality_improved_string_kernel.py
strkernels/compile_core.py
strkernels/libcore.cpython-37m-x86_64-linux-gnu.so
strkernels/__init__.py
strkernels/subsequence_string_kernel.py
strkernels/core/sqrt_diag_normalizer.c
strkernels/core/normalizer.h
strkernels/core/fixed_degree_sk.c
strkernels/core/str_kernel_matrix.c
strkernels/core/sqrt_diag_normalizer.h
strkernels/core/str_kernel.h
strkernels/core/str_kernel.c
strkernels/core/str_kernel_matrix.h
strkernels/core/locality_improved_sk.c
strkernels/core/normalizer.c
strkernels/core/locality_improved_sk.h
strkernels/core/subsequence_sk.h
strkernels/core/subsequence_sk.c
strkernels/core/fixed_degree_sk.h
strkernels.libs/libgomp-a34b3233.so.1.0.0
