Metadata-Version: 2.1
Name: strkernels
Version: 0.1.0
Summary: A Python package that implements string kernels.
Home-page: https://github.com/denilsonfbar/strkernels
Author: Denilson Fagundes Barbosa
Author-email: denilsonfbar@gmail.com
Classifier: Programming Language :: Python :: 3
Classifier: License :: OSI Approved :: GNU General Public License v3 (GPLv3)
Classifier: Operating System :: POSIX :: Linux
Requires-Python: >=3.7
License-File: LICENSE
Provides-Extra: test
Requires-Dist: pytest ; extra == 'test'
